logfire_ai.py
logfire_ai-0.1.0.dist-info/METADATA
logfire_ai-0.1.0.dist-info/WHEEL
logfire_ai-0.1.0.dist-info/top_level.txt
logfire_ai-0.1.0.dist-info/RECORD
