Metadata-Version: 2.2
Name: logfire-ai
Version: 0.1.0
Summary: WIP
Requires-Python: >=3.13
